dict_toolset/__init__.py
dict_toolset/_basic.py
dict_toolset/_compare.py
dict_toolset/_flat.py
dict_toolset/_key_extractor.py
dict_toolset/_merge.py
test/__init__.py
test/compare_test.py
test/flat_test.py
test/merge_test.py
dict_toolset-0.1.0.dist-info/LICENSE
dict_toolset-0.1.0.dist-info/METADATA
dict_toolset-0.1.0.dist-info/WHEEL
dict_toolset-0.1.0.dist-info/top_level.txt
dict_toolset-0.1.0.dist-info/RECORD
